datasette_insert_api/__init__.py
datasette_insert_api/utils.py
datasette_insert_api-0.4.dist-info/METADATA
datasette_insert_api-0.4.dist-info/WHEEL
datasette_insert_api-0.4.dist-info/entry_points.txt
datasette_insert_api-0.4.dist-info/top_level.txt
datasette_insert_api-0.4.dist-info/RECORD
