Metadata-Version: 2.1
Name: datasette-insert-api
Version: 0.4
Summary: Datasette plugin providing an API for inserting and updating data
Home-page: https://github.com/simonw/datasette-insert-api
Author: Simon Willison
License: Apache License, Version 2.0
Project-URL: Issues, https://github.com/simonw/datasette-insert-api/issues
Project-URL: CI, https://github.com/simonw/datasette-insert-api/actions
Project-URL: Changelog, https://github.com/simonw/datasette-insert-api/releases
Platform: UNKNOWN
Requires-Dist: datasette
Requires-Dist: sqlite-utils
Provides-Extra: test
Requires-Dist: pytest ; extra == 'test'
Requires-Dist: pytest-asyncio ; extra == 'test'
Requires-Dist: httpx ; extra == 'test'
Requires-Dist: datasette-auth-tokens ; extra == 'test'
